subsume/__init__.py
subsume/aligners.py
subsume/file_utils.py
subsume/speech_transformers.py
subsume/suboffset.py
subsume/subsync.py
subsume/subtitle_parsers.py
subsume/version.py
subsync/__init__.py
subsync/aligners.py
subsync/file_utils.py
subsync/speech_transformers.py
subsync/suboffset.py
subsync/subsync.py
subsync/subtitle_parsers.py
subsync/utils.py
subsync/version.py
subtools/__init__.py
subtools/aligners.py
subtools/file_utils.py
subtools/speech_transformers.py
subtools/suboffset.py
subtools/subsync.py
subtools/subtitle_parsers.py
subtools/version.py
subsume-0.2.16.dist-info/LICENSE
subsume-0.2.16.dist-info/METADATA
subsume-0.2.16.dist-info/WHEEL
subsume-0.2.16.dist-info/entry_points.txt
subsume-0.2.16.dist-info/top_level.txt
subsume-0.2.16.dist-info/RECORD
