Metadata-Version: 2.1
Name: subsume
Version: 0.2.16
Summary: Language-agnostic synchronization of subtitles with video via speech detection.
Home-page: https://github.com/smacke/subsync
Author: Stephen Macke
Author-email: stephen.macke@gmail.com
License: MIT
Platform: UNKNOWN
Classifier: Development Status :: 2 - Pre-Alpha
Classifier: Intended Audience :: Developers
Classifier: License :: OSI Approved :: MIT License
Classifier: Natural Language :: English
Classifier: Programming Language :: Python :: 2
Classifier: Programming Language :: Python :: 2.7
Classifier: Programming Language :: Python :: 3
Classifier: Programming Language :: Python :: 3.4
Classifier: Programming Language :: Python :: 3.5
Classifier: Programming Language :: Python :: 3.6
Classifier: Programming Language :: Python :: 3.7
Requires-Dist: argparse
Requires-Dist: ffmpeg-python
Requires-Dist: future
Requires-Dist: numpy (>=1.12.0)
Requires-Dist: scikit-learn (>=0.20.4)
Requires-Dist: six
Requires-Dist: srt (>=3.0.0)
Requires-Dist: tqdm
Requires-Dist: webrtcvad
